{
    "idSave": 357,
    "isFirstSession": false,
    "language": "ru",
    "promptDone": false,
    "unlockEverything": false,
    "addDisabled": false,
    "overallPoints": 337,
    "tempSaves": [
        {
            "key": "1_0006_Bottle7",
            "data": [
                0,
                0,
                0,
                0,
                0,
                0,
                0,
                0,
                0,
                0,
                0,
                0,
                0,
                0,
                0,
                0,
                0,
                224,
                7,
                0,
                0,
                28,
                56,
                0,
                0,
                2,
                64,
                0,
                0,
                1,
                128,
                0,
                128,
                0,
                0,
                1,
                64,
                0,
                0,
                2,
                32,
                0,
                0,
                4,
                32,
                192,
                3,
                4,
                32,
                32,
                4,
                4,
                16,
                16,
                8,
                8,
                16,
                8,
                16,
                8,
                16,
                8,
                16,
                8,
                16,
                8,
                16,
                8,
                240,
                15,
                16,
                12,
                240,
                31,
                8,
                12,
                224,
                63,
                4,
                6,
                224,
                195,
                3,
                6,
                224,
                0,
                0,
                6,
                192,
                0,
                0,
                3,
                112,
                0,
                128,
                1,
                56,
                0,
                192,
                0,
                120,
                30,
                120,
                0,
                232,
                255,
                63,
                0,
                144,
                227,
                7,
                0,
                192,
                1,
                0,
                0,
                0,
                0,
                0,
                0,
                0,
                0,
                0,
                0,
                0,
                0,
                0,
                0,
                0
            ]
        }
    ],
    "levels": [
        {
            "completed": false,
            "rewardUnlocked": false,
            "maxPoints": 0,
            "points": 0,
            "errors": 0
        },
        {
            "completed": false,
            "rewardUnlocked": false,
            "maxPoints": 0,
            "points": 0,
            "errors": 0
        },
        {
            "completed": false,
            "rewardUnlocked": false,
            "maxPoints": 0,
            "points": 0,
            "errors": 0
        },
        {
            "completed": false,
            "rewardUnlocked": false,
            "maxPoints": 0,
            "points": 0,
            "errors": 0
        },
        {
            "completed": false,
            "rewardUnlocked": false,
            "maxPoints": 0,
            "points": 0,
            "errors": 0
        },
        {
            "completed": false,
            "rewardUnlocked": false,
            "maxPoints": 0,
            "points": 0,
            "errors": 0
        },
        {
            "completed": false,
            "rewardUnlocked": false,
            "maxPoints": 0,
            "points": 0,
            "errors": 0
        },
        {
            "completed": false,
            "rewardUnlocked": false,
            "maxPoints": 335,
            "points": 153,
            "errors": 15
        },
        {
            "completed": false,
            "rewardUnlocked": false,
            "maxPoints": 0,
            "points": 0,
            "errors": 0
        },
        {
            "completed": false,
            "rewardUnlocked": false,
            "maxPoints": 0,
            "points": 0,
            "errors": 0
        },
        {
            "completed": false,
            "rewardUnlocked": false,
            "maxPoints": 0,
            "points": 0,
            "errors": 0
        },
        {
            "completed": false,
            "rewardUnlocked": false,
            "maxPoints": 0,
            "points": 0,
            "errors": 0
        },
        {
            "completed": false,
            "rewardUnlocked": false,
            "maxPoints": 0,
            "points": 0,
            "errors": 0
        },
        {
            "completed": false,
            "rewardUnlocked": false,
            "maxPoints": 0,
            "points": 0,
            "errors": 0
        },
        {
            "completed": false,
            "rewardUnlocked": false,
            "maxPoints": 0,
            "points": 0,
            "errors": 0
        },
        {
            "completed": false,
            "rewardUnlocked": false,
            "maxPoints": 0,
            "points": 0,
            "errors": 0
        },
        {
            "completed": false,
            "rewardUnlocked": false,
            "maxPoints": 0,
            "points": 0,
            "errors": 0
        },
        {
            "completed": false,
            "rewardUnlocked": false,
            "maxPoints": 0,
            "points": 0,
            "errors": 0
        },
        {
            "completed": false,
            "rewardUnlocked": false,
            "maxPoints": 0,
            "points": 0,
            "errors": 0
        },
        {
            "completed": false,
            "rewardUnlocked": false,
            "maxPoints": 0,
            "points": 0,
            "errors": 0
        },
        {
            "completed": false,
            "rewardUnlocked": false,
            "maxPoints": 0,
            "points": 0,
            "errors": 0
        },
        {
            "completed": false,
            "rewardUnlocked": false,
            "maxPoints": 0,
            "points": 0,
            "errors": 0
        },
        {
            "completed": false,
            "rewardUnlocked": false,
            "maxPoints": 0,
            "points": 0,
            "errors": 0
        },
        {
            "completed": false,
            "rewardUnlocked": false,
            "maxPoints": 0,
            "points": 0,
            "errors": 0
        },
        {
            "completed": false,
            "rewardUnlocked": false,
            "maxPoints": 0,
            "points": 0,
            "errors": 0
        },
        {
            "completed": false,
            "rewardUnlocked": false,
            "maxPoints": 0,
            "points": 0,
            "errors": 0
        },
        {
            "completed": false,
            "rewardUnlocked": false,
            "maxPoints": 0,
            "points": 0,
            "errors": 0
        },
        {
            "completed": false,
            "rewardUnlocked": false,
            "maxPoints": 0,
            "points": 0,
            "errors": 0
        },
        {
            "completed": false,
            "rewardUnlocked": false,
            "maxPoints": 0,
            "points": 0,
            "errors": 0
        },
        {
            "completed": false,
            "rewardUnlocked": false,
            "maxPoints": 0,
            "points": 0,
            "errors": 0
        },
        {
            "completed": false,
            "rewardUnlocked": false,
            "maxPoints": 0,
            "points": 0,
            "errors": 0
        },
        {
            "completed": false,
            "rewardUnlocked": false,
            "maxPoints": 0,
            "points": 0,
            "errors": 0
        },
        {
            "completed": false,
            "rewardUnlocked": false,
            "maxPoints": 0,
            "points": 0,
            "errors": 0
        },
        {
            "completed": false,
            "rewardUnlocked": false,
            "maxPoints": 0,
            "points": 0,
            "errors": 0
        },
        {
            "completed": false,
            "rewardUnlocked": false,
            "maxPoints": 0,
            "points": 0,
            "errors": 0
        },
        {
            "completed": false,
            "rewardUnlocked": false,
            "maxPoints": 0,
            "points": 0,
            "errors": 0
        },
        {
            "completed": false,
            "rewardUnlocked": false,
            "maxPoints": 0,
            "points": 0,
            "errors": 0
        },
        {
            "completed": false,
            "rewardUnlocked": false,
            "maxPoints": 0,
            "points": 0,
            "errors": 0
        },
        {
            "completed": false,
            "rewardUnlocked": false,
            "maxPoints": 0,
            "points": 0,
            "errors": 0
        },
        {
            "completed": false,
            "rewardUnlocked": false,
            "maxPoints": 0,
            "points": 0,
            "errors": 0
        },
        {
            "completed": false,
            "rewardUnlocked": false,
            "maxPoints": 0,
            "points": 0,
            "errors": 0
        },
        {
            "completed": false,
            "rewardUnlocked": false,
            "maxPoints": 0,
            "points": 0,
            "errors": 0
        },
        {
            "completed": false,
            "rewardUnlocked": false,
            "maxPoints": 0,
            "points": 0,
            "errors": 0
        },
        {
            "completed": false,
            "rewardUnlocked": false,
            "maxPoints": 0,
            "points": 0,
            "errors": 0
        },
        {
            "completed": false,
            "rewardUnlocked": false,
            "maxPoints": 0,
            "points": 0,
            "errors": 0
        },
        {
            "completed": false,
            "rewardUnlocked": false,
            "maxPoints": 0,
            "points": 0,
            "errors": 0
        },
        {
            "completed": false,
            "rewardUnlocked": false,
            "maxPoints": 0,
            "points": 0,
            "errors": 0
        },
        {
            "completed": false,
            "rewardUnlocked": false,
            "maxPoints": 0,
            "points": 0,
            "errors": 0
        },
        {
            "completed": false,
            "rewardUnlocked": false,
            "maxPoints": 0,
            "points": 0,
            "errors": 0
        },
        {
            "completed": false,
            "rewardUnlocked": false,
            "maxPoints": 0,
            "points": 0,
            "errors": 0
        }
    ]
}